openehr_sdk/__init__.py
openehr_sdk/aql/__init__.py
openehr_sdk/aql/builder.py
openehr_sdk/client/__init__.py
openehr_sdk/client/ehrbase.py
openehr_sdk/rm/__init__.py
openehr_sdk/rm/rm_types.py
openehr_sdk/serialization/__init__.py
openehr_sdk/serialization/canonical.py
openehr_sdk/serialization/flat.py
openehr_sdk/templates/__init__.py
openehr_sdk/templates/builder_generator.py
openehr_sdk/templates/builders.py
openehr_sdk/templates/opt_parser.py
oehrpy-0.1.1.dist-info/METADATA
oehrpy-0.1.1.dist-info/WHEEL
oehrpy-0.1.1.dist-info/licenses/LICENSE
oehrpy-0.1.1.dist-info/RECORD
