Metadata-Version: 2.3
Name: oehrpy
Version: 0.1.1
Summary: A Python SDK for openEHR with type-safe Reference Model classes, template builders, and EHRBase client
Project-URL: Homepage, https://github.com/platzhersh/oehrpy
Project-URL: Documentation, https://github.com/platzhersh/oehrpy#readme
Project-URL: Repository, https://github.com/platzhersh/oehrpy
Project-URL: Issues, https://github.com/platzhersh/oehrpy/issues
Author: Open CIS Project
License: MIT
License-File: LICENSE
Keywords: aql,clinical,ehr,ehrbase,healthcare,openehr,pydantic,sdk
Classifier: Development Status :: 3 - Alpha
Classifier: Intended Audience :: Developers
Classifier: Intended Audience :: Healthcare Industry
Classifier: License :: OSI Approved :: MIT License
Classifier: Programming Language :: Python :: 3
Classifier: Programming Language :: Python :: 3.10
Classifier: Programming Language :: Python :: 3.11
Classifier: Programming Language :: Python :: 3.12
Classifier: Programming Language :: Python :: 3.13
Classifier: Topic :: Scientific/Engineering :: Medical Science Apps.
Classifier: Typing :: Typed
Requires-Python: >=3.10
Requires-Dist: defusedxml>=0.7
Requires-Dist: httpx>=0.25
Requires-Dist: pydantic>=2.0
Provides-Extra: dev
Requires-Dist: mypy>=1.0; extra == 'dev'
Requires-Dist: pytest-asyncio>=0.21; extra == 'dev'
Requires-Dist: pytest>=7.0; extra == 'dev'
Requires-Dist: ruff>=0.1; extra == 'dev'
Requires-Dist: types-defusedxml>=0.7; extra == 'dev'
Provides-Extra: generator
Requires-Dist: jinja2>=3.0; extra == 'generator'
Requires-Dist: lxml>=4.9; extra == 'generator'
